README.rst
packer.py
setup.py
python_packer.egg-info/PKG-INFO
python_packer.egg-info/SOURCES.txt
python_packer.egg-info/dependency_links.txt
python_packer.egg-info/requires.txt
python_packer.egg-info/top_level.txt