Metadata-Version: 1.1
Name: python-packer
Version: 0.1.1
Summary: A Python interface for Hashicorp's Packer
Home-page: https://github.com/nir0s/python-packer
Author: nir0s
Author-email: nir36g@gmail.com
License: LICENSE
Platform: All
Classifier: Programming Language :: Python
Classifier: Natural Language :: English
Classifier: Environment :: Console
Classifier: Intended Audience :: Developers
Classifier: Intended Audience :: Information Technology
Classifier: Intended Audience :: System Administrators
Classifier: License :: OSI Approved :: Apache Software License
Classifier: Operating System :: POSIX :: Linux
Classifier: Operating System :: Microsoft
Classifier: Topic :: Software Development :: Libraries :: Python Modules
